README.md
moder.py
setup.cfg
setup.py
ext/__init__.py
ext/peertool
ext/rnaseqc
ext/SPOT/dirichlet_multinomial.py
ext/SPOT/dirichlet_multinomial.stan
ext/SPOT/spot.py
ext/callOutliers/__init__.py
ext/callOutliers/anevadot.py
ext/callOutliers/collapse_annotation.py
ext/callOutliers/gtf2bed12.py
ext/callOutliers/resemble_outliersFinder.py
ext/callOutliers/zscore_outliersFinder.py
ext/leafcutter/bam2junc.sh
ext/leafcutter/bed2junc.pl
ext/leafcutter/filter_cs.py
ext/leafcutter/get_cluster_gene.py
ext/leafcutter/leafcutter_cluster.py
ext/leafcutter/sam2bed.pl
ext/phaser/call_read_variant_map.py
ext/phaser/phaser.py
ext/phaser/phaser_annotate.py
ext/phaser/phaser_gene_ae.py
ext/phaser/read_variant_map.py
glh_test.egg-info/PKG-INFO
glh_test.egg-info/SOURCES.txt
glh_test.egg-info/dependency_links.txt
glh_test.egg-info/requires.txt
glh_test.egg-info/top_level.txt
src/__init__.py
src/ase.py
src/expression.py
src/splicing.py