Metadata-Version: 2.1
Name: glh-test
Version: 0.0.2
Summary: Molecular Outlier DEtection from Rna-seq data
Home-page: https://github.com/Xu-Dong/MODER/tree/singleTissue
Author: GongLihai
Author-email: gonglihai@outlook.com
License: GNU GENERAL PUBLIC LICENSE
Platform: UNKNOWN
